dbq/__init__.py
dbq/main.py
dbq-0.9.0.dist-info/LICENSE
dbq-0.9.0.dist-info/METADATA
dbq-0.9.0.dist-info/WHEEL
dbq-0.9.0.dist-info/entry_points.txt
dbq-0.9.0.dist-info/top_level.txt
dbq-0.9.0.dist-info/RECORD
