Metadata-Version: 2.1
Name: dbq
Version: 0.9.0
Summary: Run a query on Databricks
Home-page: https://github.com/getyourguide/dbq
Author: GetYourGuide GmbH
License: Apache License, Version 2.0
Platform: UNKNOWN
Requires-Dist: databricks-dbapi
Requires-Dist: tabulate
